kperf/__init__.py
kperf/draw.py
kperf/main.py
kperf/perf.py
kperf/proc.py
kperf/system.py
kperf/utils.py
kperf-0.0.2.dist-info/LICENSE
kperf-0.0.2.dist-info/METADATA
kperf-0.0.2.dist-info/WHEEL
kperf-0.0.2.dist-info/entry_points.txt
kperf-0.0.2.dist-info/RECORD
