Metadata-Version: 2.1
Name: kperf
Version: 0.0.2
Summary: linux kernel profiler
License: MIT
Author: luzhixing12345
Author-email: luzhixing12345@163.com
Requires-Python: >=3.9,<4.0
Classifier: License :: OSI Approved :: MIT License
Classifier: Programming Language :: Python :: 3
Classifier: Programming Language :: Python :: 3.9
Classifier: Programming Language :: Python :: 3.10
Classifier: Programming Language :: Python :: 3.11
Classifier: Programming Language :: Python :: 3.12
Requires-Dist: paperplotlib
Requires-Dist: prettytable
Requires-Dist: psutil
